Workbook

Sheet Dashboard
A1: BANK FINANCIAL DATA QUALITY DASHBOARD
A3: Metric | B3: Value | C3: Interpretation
A4: Raw rows | B4: =COUNTA(Raw_Data!A2:A14) | C4: Includes all source rows, including seeded duplicate.
A5: Unique banks | B5: =SUMPRODUCT((Raw_Data!A2:A14<>)/COUNTIF(Raw_Data!A2:A{raw_last},Raw_Data!A2:A{raw_last}&)) | C5: Distinct bank IDs; formula may vary by Excel version.
A6: Missing critical-value rows | B6: =COUNTIF(Validation!D2:D14,"EXCEPTION") | C6: Assets, equity, or net income missing.
A7: Duplicate bank-period rows flagged | B7: =COUNTIF(Validation!E2:E14,"EXCEPTION") | C7: Each row belonging to a duplicated bank-period is flagged.
A8: Balance sheet exceptions | B8: =COUNTIF(Validation!F2:F14,"EXCEPTION") | C8: Assets vs liabilities plus equity, tolerance 1.
A9: NPL logic exceptions | B9: =COUNTIF(Validation!G2:G14,"EXCEPTION") | C9: NPL amount exceeds gross loans.
A10: Negative interest expense exceptions | B10: =COUNTIF(Validation!H2:H14,"EXCEPTION") | C10: Review sign convention and source.
A11: Deposit exceptions | B11: =COUNTIF(Validation!I2:I14,"EXCEPTION") | C11: Deposits are zero or negative.
A12: Ratio review/check rows | B12: =COUNTIF(Validation!O2:O14,"CHECK")+COUNTIF(Validation!O2:O14,"REVIEW") | C12: Ratios require review; NIM is a simplified proxy.
A13: Open exception log items | B13: =COUNTIF(Exception_Log!I2:I100,"Open") | C13: Update status after source-based investigation.
A16: Use notes
A17: This is synthetic practice data, not Moody's data or a regulatory reporting template.
A18: Do not auto-correct exceptions. Verify the source, log the decision, and preserve raw lineage.
A19: NIM proxy uses (interest income - interest expense) / total assets because average earning assets are not supplied.
A20: All monetary values are fictional currency units; ratios are stored as decimals.

Sheet Raw_Data
A1: bank_id | B1: bank_name | C1: country | D1: report_date | E1: accounting_standard | F1: source_name | G1: total_assets | H1: total_liabilities | I1: total_equity | J1: gross_loans | K1: npl_amount | L1: total_deposits | M1: interest_income | N1: interest_expense | O1: net_income | P1: risk_weighted_assets | Q1: regulatory_capital | R1: npl_ratio_reported | S1: car_reported | T1: roa_reported | U1: roe_reported | V1: nim_reported | W1: allowance_for_loan_losses
A2: B001 | B2: Northstar Bank | C2: India | D2: 2025-03-31 | E2: IFRS | F2: Annual Report | G2: 125000 | H2: 112000 | I2: 13000 | J2: 100000 | K2: 8000 | L2: 5000 | M2: 2200 | N2: 700 | O2: 1200 | P2: 130000 | Q2: 15000 | R2: 0.145 | S2: 0.115 | T2: 0.028 | U2: 0.012 | V2: 0.105 | W2: 0.015
A3: B002 | B3: Rivergate Bank | C3: India | D3: 2025-03-31 | E3: IFRS | F3: Annual Report | G3: 98000 | H3: 90000 | I3: 8000 | J3: 76000 | K3: 6000 | L3: 4000 | M3: 1800 | N3: 550 | O3: 900 | P3: 95000 | Q3: 10200 | R3: 0.132 | S3: 0.108 | T3: 0.031 | U3: 0.014 | V3: 0.092 | W3: 0.018
A4: B003 | B4: Summit Commercial Bank | C4: UK | D4: 2025-03-31 | E4: IFRS | F4: Annual Report | G4: 210000 | H4: 194000 | J4: 165000 | K4: 12000 | L4: 9000 | M4: 3100 | N4: 950 | O4: 2100 | P4: 170000 | Q4: 19800 | R4: 0.114 | S4: 0.094 | T4: 0.026 | U4: 0.01 | V4: 0.098 | W4: 0.013
A5: B004 | B5: Cedar Trust Bank | C5: US | D5: 2025-03-31 | E5: US_GAAP | F5: Annual Report | G5: 165000 | H5: 161000 | I5: 14000 | J5: 135000 | K5: 10000 | L5: 7000 | M5: 2700 | N5: 820 | O5: 1700 | P5: 145000 | Q5: 16800 | R5: 0.12 | S5: 0.096 | T5: 0.024 | U5: 0.009 | V5: 0.101 | W5: 0.014
A6: B005 | B6: BluePeak Bank | C6: Singapore | D6: 2025-03-31 | E6: IFRS | F6: Annual Report | G6: 76000 | H6: 70000 | I6: 6000 | J6: 58000 | K6: 65000 | L6: 3000 | M6: 1400 | N6: 430 | O6: 600 | P6: 65000 | Q6: 7400 | R6: 0.118 | S6: 0.097 | T6: 0.029 | U6: 0.011 | V6: 0.088 | W6: 0.016
A7: B006 | B7: Oakline Bank | C7: India | D7: 2025-03-31 | E7: IFRS | F7: Annual Report | G7: 88000 | H7: 81000 | I7: 7000 | J7: 69000 | K7: 5200 | L7: 3600 | M7: 1500 | N7: -460 | O7: 800 | P7: 78000 | Q7: 8900 | R7: 0.125 | S7: 0.101 | T7: 0.03 | U7: 0.013 | V7: 0.094 | W7: 0.017
A8: B007 | B8: Meridian Bank | C8: Canada | D8: 2025-03-31 | E8: IFRS | F8: Annual Report | G8: 142000 | H8: 130000 | I8: 12000 | J8: 108000 | K8: 8500 | L8: 6200 | M8: 2400 | N8: 730 | P8: 115000 | Q8: 13900 | R8: 0.119 | S8: 0.098 | T8: 0.027 | U8: 0.01 | V8: 0.099 | W8: 0.014
A9: B008 | B9: Pinecrest Bank | C9: Australia | D9: 2025-03-31 | E9: IFRS | F9: Annual Report | G9: 66000 | H9: 61000 | I9: 5000 | J9: 49000 | K9: 3800 | L9: 2600 | M9: 1100 | N9: 350 | O9: 500 | P9: 54000 | Q9: 6300 | R9: 0.118 | S9: 0.096 | T9: 0.028 | U9: 0.012 | V9: 0.091 | W9: 0.016
A10: B009 | B10: Harborview Bank | C10: India | D10: 2025-03-31 | E10: IFRS | F10: Annual Report | G10: 105000 | H10: 96000 | I10: 9000 | J10: 82000 | K10: 6500 | L10: 0 | M10: 1900 | N10: 600 | O10: 1000 | P10: 92000 | Q10: 11000 | R10: 0.129 | S10: 0.105 | T10: 0.029 | U10: 0.011 | V10: 0.097 | W10: 0.015
A11: B010 | B11: Redwood Bank | C11: UK | D11: 2025-03-31 | E11: IFRS | F11: Annual Report | G11: 155000 | H11: 143000 | I11: 12000 | J11: 121000 | K11: 9200 | L11: 6500 | M11: 2500 | N11: 780 | O11: 1400 | P11: 128000 | Q11: 25000 | R11: 0.123 | S11: 0.099 | T11: 0.025 | U11: 0.01 | V11: 0.1 | W11: 0.014
A12: B011 | B12: Eastwind Bank | C12: US | D12: 2025-03-31 | E12: US_GAAP | F12: Annual Report | G12: 92000 | H12: 85000 | I12: 7000 | J12: 72000 | K12: 5400 | L12: 3900 | M12: 1600 | N12: 490 | O12: 750 | P12: 78000 | Q12: 9100 | R12: 0.122 | S12: 0.099 | T12: 0.027 | U12: 0.011 | V12: 0.095 | W12: 0.016
A13: B012 | B13: Silverfern Bank | C13: Singapore | D13: 2025-03-31 | E13: IFRS | F13: Annual Report | G13: 118000 | H13: 108000 | I13: 10000 | J13: 91000 | K13: 7000 | L13: 5000 | M13: 2100 | N13: 650 | O13: 1100 | P13: 98000 | Q13: 11800 | R13: 0.123 | S13: 0.1 | T13: 0.028 | U13: 0.012 | V13: 0.096 | W13: 0.015
A14: B002 | B14: Rivergate Bank | C14: India | D14: 2025-03-31 | E14: IFRS | F14: Vendor Feed | G14: 98000 | H14: 90000 | I14: 8000 | J14: 76000 | K14: 6000 | L14: 4000 | M14: 1800 | N14: 550 | O14: 900 | P14: 95000 | Q14: 10200 | R14: 0.132 | S14: 0.108 | T14: 0.031 | U14: 0.014 | V14: 0.092 | W14: 0.018

Sheet Source_Comparison
A1: bank_id | B1: bank_name | C1: report_date | D1: source_name | E1: total_assets | F1: total_liabilities | G1: total_equity | H1: net_income
A2: B001 | B2: Northstar Bank | C2: 2025-03-31 | D2: Annual Report | E2: 125000 | F2: 112000 | G2: 13000 | H2: 1200
A3: B001 | B3: Northstar Bank | C3: 2025-03-31 | D3: Vendor Feed | E3: 125000 | F3: 112000 | G3: 13000 | H3: 1200
A4: B002 | B4: Rivergate Bank | C4: 2025-03-31 | D4: Annual Report | E4: 98000 | F4: 90000 | G4: 8000 | H4: 900
A5: B002 | B5: Rivergate Bank | C5: 2025-03-31 | D5: Vendor Feed | E5: 98000 | F5: 90000 | G5: 8000 | H5: 900
A6: B003 | B6: Summit Commercial Bank | C6: 2025-03-31 | D6: Annual Report | E6: 210000 | F6: 194000 | H6: 2100
A7: B003 | B7: Summit Commercial Bank | C7: 2025-03-31 | D7: Vendor Feed | E7: 210000 | F7: 194000 | H7: 2100
A8: B004 | B8: Cedar Trust Bank | C8: 2025-03-31 | D8: Annual Report | E8: 165000 | F8: 161000 | G8: 14000 | H8: 1700
A9: B004 | B9: Cedar Trust Bank | C9: 2025-03-31 | D9: Vendor Feed | E9: 165000 | F9: 161000 | G9: 14000 | H9: 1700
A10: B005 | B10: BluePeak Bank | C10: 2025-03-31 | D10: Annual Report | E10: 76000 | F10: 70000 | G10: 6000 | H10: 600
A11: B005 | B11: BluePeak Bank | C11: 2025-03-31 | D11: Vendor Feed | E11: 76000 | F11: 70000 | G11: 6000 | H11: 600
A12: B006 | B12: Oakline Bank | C12: 2025-03-31 | D12: Annual Report | E12: 88000 | F12: 81000 | G12: 7000 | H12: 800
A13: B006 | B13: Oakline Bank | C13: 2025-03-31 | D13: Vendor Feed | E13: 88000 | F13: 81000 | G13: 7000 | H13: 800
A14: B007 | B14: Meridian Bank | C14: 2025-03-31 | D14: Annual Report | E14: 142000 | F14: 130000 | G14: 12000
A15: B007 | B15: Meridian Bank | C15: 2025-03-31 | D15: Vendor Feed | E15: 142000 | F15: 130000 | G15: 12000
A16: B008 | B16: Pinecrest Bank | C16: 2025-03-31 | D16: Annual Report | E16: 66000 | F16: 61000 | G16: 5000 | H16: 500
A17: B008 | B17: Pinecrest Bank | C17: 2025-03-31 | D17: Vendor Feed | E17: 68000 | F17: 61000 | G17: 5000 | H17: 500
A18: B009 | B18: Harborview Bank | C18: 2025-03-31 | D18: Annual Report | E18: 105000 | F18: 96000 | G18: 9000 | H18: 1000
A19: B009 | B19: Harborview Bank | C19: 2025-03-31 | D19: Vendor Feed | E19: 105000 | F19: 96000 | G19: 9000 | H19: 1000
A20: B010 | B20: Redwood Bank | C20: 2025-03-31 | D20: Annual Report | E20: 155000 | F20: 143000 | G20: 12000 | H20: 1400
A21: B010 | B21: Redwood Bank | C21: 2025-03-31 | D21: Vendor Feed | E21: 155000 | F21: 143000 | G21: 12000 | H21: 1400
A22: B011 | B22: Eastwind Bank | C22: 2025-03-31 | D22: Annual Report | E22: 92000 | F22: 85000 | G22: 7000 | H22: 750
A23: B011 | B23: Eastwind Bank | C23: 2025-03-31 | D23: Vendor Feed | E23: 92000 | F23: 85000 | G23: 7000 | H23: 9300
A24: B012 | B24: Silverfern Bank | C24: 2025-03-31 | D24: Annual Report | E24: 118000 | F24: 108000 | G24: 10000 | H24: 1100
A25: B012 | B25: Silverfern Bank | C25: 2025-03-31 | D25: Vendor Feed | E25: 118000 | F25: 108000 | G25: 10000 | H25: 1100

Sheet Validation
A1: bank_id | B1: bank_name | C1: report_date | D1: Missing Critical? | E1: Duplicate Bank-Period? | F1: Balance Sheet Check | G1: NPL Check | H1: Interest Expense Check | I1: Deposit Check | J1: Calculated NPL Ratio | K1: Calculated CAR | L1: Calculated ROA | M1: Calculated ROE | N1: NIM Proxy | O1: Ratio Check | P1: Review Status | Q1: Reviewer Notes
A2: =Raw_Data!A2 | B2: =Raw_Data!B2 | C2: =Raw_Data!D2 | D2: =IF(OR(Raw_Data!G2="",Raw_Data!I2="",Raw_Data!O2=""),"EXCEPTION","PASS") | E2: =IF(COUNTIFS(Raw_Data!A:A,A2,Raw_Data!D:D,C2)>1,"EXCEPTION","PASS") | F2: =IF(OR(Raw_Data!G2="",Raw_Data!H2="",Raw_Data!I2=""),"REVIEW",IF(ABS(Raw_Data!G2-Raw_Data!H2-Raw_Data!I2)>1,"EXCEPTION","PASS")) | G2: =IF(OR(Raw_Data!K2="",Raw_Data!J2=""),"REVIEW",IF(Raw_Data!K2>Raw_Data!J2,"EXCEPTION","PASS")) | H2: =IF(Raw_Data!N2="","REVIEW",IF(Raw_Data!N2<0,"EXCEPTION","PASS")) | I2: =IF(Raw_Data!L2="","REVIEW",IF(Raw_Data!L2<=0,"EXCEPTION","PASS")) | J2: =IFERROR(Raw_Data!K2/Raw_Data!J2,"") | K2: =IFERROR(Raw_Data!Q2/Raw_Data!P2,"") | L2: =IFERROR(Raw_Data!O2/Raw_Data!G2,"") | M2: =IFERROR(Raw_Data!O2/Raw_Data!I2,"") | N2: =IFERROR((Raw_Data!M2-Raw_Data!N2)/Raw_Data!G2,"") | O2: =IF(OR(J2="",K2="",L2="",M2="",N2=""),"REVIEW",IF(OR(ABS(J2-Raw_Data!R2)>0.005,ABS(K2-Raw_Data!S2)>0.005,ABS(L2-Raw_Data!T2)>0.005,ABS(M2-Raw_Data!U2)>0.005,ABS(N2-Raw_Data!V2)>0.005),"CHECK","PASS")) | P2: Open
A3: =Raw_Data!A3 | B3: =Raw_Data!B3 | C3: =Raw_Data!D3 | D3: =IF(OR(Raw_Data!G3="",Raw_Data!I3="",Raw_Data!O3=""),"EXCEPTION","PASS") | E3: =IF(COUNTIFS(Raw_Data!A:A,A3,Raw_Data!D:D,C3)>1,"EXCEPTION","PASS") | F3: =IF(OR(Raw_Data!G3="",Raw_Data!H3="",Raw_Data!I3=""),"REVIEW",IF(ABS(Raw_Data!G3-Raw_Data!H3-Raw_Data!I3)>1,"EXCEPTION","PASS")) | G3: =IF(OR(Raw_Data!K3="",Raw_Data!J3=""),"REVIEW",IF(Raw_Data!K3>Raw_Data!J3,"EXCEPTION","PASS")) | H3: =IF(Raw_Data!N3="","REVIEW",IF(Raw_Data!N3<0,"EXCEPTION","PASS")) | I3: =IF(Raw_Data!L3="","REVIEW",IF(Raw_Data!L3<=0,"EXCEPTION","PASS")) | J3: =IFERROR(Raw_Data!K3/Raw_Data!J3,"") | K3: =IFERROR(Raw_Data!Q3/Raw_Data!P3,"") | L3: =IFERROR(Raw_Data!O3/Raw_Data!G3,"") | M3: =IFERROR(Raw_Data!O3/Raw_Data!I3,"") | N3: =IFERROR((Raw_Data!M3-Raw_Data!N3)/Raw_Data!G3,"") | O3: =IF(OR(J3="",K3="",L3="",M3="",N3=""),"REVIEW",IF(OR(ABS(J3-Raw_Data!R3)>0.005,ABS(K3-Raw_Data!S3)>0.005,ABS(L3-Raw_Data!T3)>0.005,ABS(M3-Raw_Data!U3)>0.005,ABS(N3-Raw_Data!V3)>0.005),"CHECK","PASS")) | P3: Open
A4: =Raw_Data!A4 | B4: =Raw_Data!B4 | C4: =Raw_Data!D4 | D4: =IF(OR(Raw_Data!G4="",Raw_Data!I4="",Raw_Data!O4=""),"EXCEPTION","PASS") | E4: =IF(COUNTIFS(Raw_Data!A:A,A4,Raw_Data!D:D,C4)>1,"EXCEPTION","PASS") | F4: =IF(OR(Raw_Data!G4="",Raw_Data!H4="",Raw_Data!I4=""),"REVIEW",IF(ABS(Raw_Data!G4-Raw_Data!H4-Raw_Data!I4)>1,"EXCEPTION","PASS")) | G4: =IF(OR(Raw_Data!K4="",Raw_Data!J4=""),"REVIEW",IF(Raw_Data!K4>Raw_Data!J4,"EXCEPTION","PASS")) | H4: =IF(Raw_Data!N4="","REVIEW",IF(Raw_Data!N4<0,"EXCEPTION","PASS")) | I4: =IF(Raw_Data!L4="","REVIEW",IF(Raw_Data!L4<=0,"EXCEPTION","PASS")) | J4: =IFERROR(Raw_Data!K4/Raw_Data!J4,"") | K4: =IFERROR(Raw_Data!Q4/Raw_Data!P4,"") | L4: =IFERROR(Raw_Data!O4/Raw_Data!G4,"") | M4: =IFERROR(Raw_Data!O4/Raw_Data!I4,"") | N4: =IFERROR((Raw_Data!M4-Raw_Data!N4)/Raw_Data!G4,"") | O4: =IF(OR(J4="",K4="",L4="",M4="",N4=""),"REVIEW",IF(OR(ABS(J4-Raw_Data!R4)>0.005,ABS(K4-Raw_Data!S4)>0.005,ABS(L4-Raw_Data!T4)>0.005,ABS(M4-Raw_Data!U4)>0.005,ABS(N4-Raw_Data!V4)>0.005),"CHECK","PASS")) | P4: Open
A5: =Raw_Data!A5 | B5: =Raw_Data!B5 | C5: =Raw_Data!D5 | D5: =IF(OR(Raw_Data!G5="",Raw_Data!I5="",Raw_Data!O5=""),"EXCEPTION","PASS") | E5: =IF(COUNTIFS(Raw_Data!A:A,A5,Raw_Data!D:D,C5)>1,"EXCEPTION","PASS") | F5: =IF(OR(Raw_Data!G5="",Raw_Data!H5="",Raw_Data!I5=""),"REVIEW",IF(ABS(Raw_Data!G5-Raw_Data!H5-Raw_Data!I5)>1,"EXCEPTION","PASS")) | G5: =IF(OR(Raw_Data!K5="",Raw_Data!J5=""),"REVIEW",IF(Raw_Data!K5>Raw_Data!J5,"EXCEPTION","PASS")) | H5: =IF(Raw_Data!N5="","REVIEW",IF(Raw_Data!N5<0,"EXCEPTION","PASS")) | I5: =IF(Raw_Data!L5="","REVIEW",IF(Raw_Data!L5<=0,"EXCEPTION","PASS")) | J5: =IFERROR(Raw_Data!K5/Raw_Data!J5,"") | K5: =IFERROR(Raw_Data!Q5/Raw_Data!P5,"") | L5: =IFERROR(Raw_Data!O5/Raw_Data!G5,"") | M5: =IFERROR(Raw_Data!O5/Raw_Data!I5,"") | N5: =IFERROR((Raw_Data!M5-Raw_Data!N5)/Raw_Data!G5,"") | O5: =IF(OR(J5="",K5="",L5="",M5="",N5=""),"REVIEW",IF(OR(ABS(J5-Raw_Data!R5)>0.005,ABS(K5-Raw_Data!S5)>0.005,ABS(L5-Raw_Data!T5)>0.005,ABS(M5-Raw_Data!U5)>0.005,ABS(N5-Raw_Data!V5)>0.005),"CHECK","PASS")) | P5: Open
A6: =Raw_Data!A6 | B6: =Raw_Data!B6 | C6: =Raw_Data!D6 | D6: =IF(OR(Raw_Data!G6="",Raw_Data!I6="",Raw_Data!O6=""),"EXCEPTION","PASS") | E6: =IF(COUNTIFS(Raw_Data!A:A,A6,Raw_Data!D:D,C6)>1,"EXCEPTION","PASS") | F6: =IF(OR(Raw_Data!G6="",Raw_Data!H6="",Raw_Data!I6=""),"REVIEW",IF(ABS(Raw_Data!G6-Raw_Data!H6-Raw_Data!I6)>1,"EXCEPTION","PASS")) | G6: =IF(OR(Raw_Data!K6="",Raw_Data!J6=""),"REVIEW",IF(Raw_Data!K6>Raw_Data!J6,"EXCEPTION","PASS")) | H6: =IF(Raw_Data!N6="","REVIEW",IF(Raw_Data!N6<0,"EXCEPTION","PASS")) | I6: =IF(Raw_Data!L6="","REVIEW",IF(Raw_Data!L6<=0,"EXCEPTION","PASS")) | J6: =IFERROR(Raw_Data!K6/Raw_Data!J6,"") | K6: =IFERROR(Raw_Data!Q6/Raw_Data!P6,"") | L6: =IFERROR(Raw_Data!O6/Raw_Data!G6,"") | M6: =IFERROR(Raw_Data!O6/Raw_Data!I6,"") | N6: =IFERROR((Raw_Data!M6-Raw_Data!N6)/Raw_Data!G6,"") | O6: =IF(OR(J6="",K6="",L6="",M6="",N6=""),"REVIEW",IF(OR(ABS(J6-Raw_Data!R6)>0.005,ABS(K6-Raw_Data!S6)>0.005,ABS(L6-Raw_Data!T6)>0.005,ABS(M6-Raw_Data!U6)>0.005,ABS(N6-Raw_Data!V6)>0.005),"CHECK","PASS")) | P6: Open
A7: =Raw_Data!A7 | B7: =Raw_Data!B7 | C7: =Raw_Data!D7 | D7: =IF(OR(Raw_Data!G7="",Raw_Data!I7="",Raw_Data!O7=""),"EXCEPTION","PASS") | E7: =IF(COUNTIFS(Raw_Data!A:A,A7,Raw_Data!D:D,C7)>1,"EXCEPTION","PASS") | F7: =IF(OR(Raw_Data!G7="",Raw_Data!H7="",Raw_Data!I7=""),"REVIEW",IF(ABS(Raw_Data!G7-Raw_Data!H7-Raw_Data!I7)>1,"EXCEPTION","PASS")) | G7: =IF(OR(Raw_Data!K7="",Raw_Data!J7=""),"REVIEW",IF(Raw_Data!K7>Raw_Data!J7,"EXCEPTION","PASS")) | H7: =IF(Raw_Data!N7="","REVIEW",IF(Raw_Data!N7<0,"EXCEPTION","PASS")) | I7: =IF(Raw_Data!L7="","REVIEW",IF(Raw_Data!L7<=0,"EXCEPTION","PASS")) | J7: =IFERROR(Raw_Data!K7/Raw_Data!J7,"") | K7: =IFERROR(Raw_Data!Q7/Raw_Data!P7,"") | L7: =IFERROR(Raw_Data!O7/Raw_Data!G7,"") | M7: =IFERROR(Raw_Data!O7/Raw_Data!I7,"") | N7: =IFERROR((Raw_Data!M7-Raw_Data!N7)/Raw_Data!G7,"") | O7: =IF(OR(J7="",K7="",L7="",M7="",N7=""),"REVIEW",IF(OR(ABS(J7-Raw_Data!R7)>0.005,ABS(K7-Raw_Data!S7)>0.005,ABS(L7-Raw_Data!T7)>0.005,ABS(M7-Raw_Data!U7)>0.005,ABS(N7-Raw_Data!V7)>0.005),"CHECK","PASS")) | P7: Open
A8: =Raw_Data!A8 | B8: =Raw_Data!B8 | C8: =Raw_Data!D8 | D8: =IF(OR(Raw_Data!G8="",Raw_Data!I8="",Raw_Data!O8=""),"EXCEPTION","PASS") | E8: =IF(COUNTIFS(Raw_Data!A:A,A8,Raw_Data!D:D,C8)>1,"EXCEPTION","PASS") | F8: =IF(OR(Raw_Data!G8="",Raw_Data!H8="",Raw_Data!I8=""),"REVIEW",IF(ABS(Raw_Data!G8-Raw_Data!H8-Raw_Data!I8)>1,"EXCEPTION","PASS")) | G8: =IF(OR(Raw_Data!K8="",Raw_Data!J8=""),"REVIEW",IF(Raw_Data!K8>Raw_Data!J8,"EXCEPTION","PASS")) | H8: =IF(Raw_Data!N8="","REVIEW",IF(Raw_Data!N8<0,"EXCEPTION","PASS")) | I8: =IF(Raw_Data!L8="","REVIEW",IF(Raw_Data!L8<=0,"EXCEPTION","PASS")) | J8: =IFERROR(Raw_Data!K8/Raw_Data!J8,"") | K8: =IFERROR(Raw_Data!Q8/Raw_Data!P8,"") | L8: =IFERROR(Raw_Data!O8/Raw_Data!G8,"") | M8: =IFERROR(Raw_Data!O8/Raw_Data!I8,"") | N8: =IFERROR((Raw_Data!M8-Raw_Data!N8)/Raw_Data!G8,"") | O8: =IF(OR(J8="",K8="",L8="",M8="",N8=""),"REVIEW",IF(OR(ABS(J8-Raw_Data!R8)>0.005,ABS(K8-Raw_Data!S8)>0.005,ABS(L8-Raw_Data!T8)>0.005,ABS(M8-Raw_Data!U8)>0.005,ABS(N8-Raw_Data!V8)>0.005),"CHECK","PASS")) | P8: Open
A9: =Raw_Data!A9 | B9: =Raw_Data!B9 | C9: =Raw_Data!D9 | D9: =IF(OR(Raw_Data!G9="",Raw_Data!I9="",Raw_Data!O9=""),"EXCEPTION","PASS") | E9: =IF(COUNTIFS(Raw_Data!A:A,A9,Raw_Data!D:D,C9)>1,"EXCEPTION","PASS") | F9: =IF(OR(Raw_Data!G9="",Raw_Data!H9="",Raw_Data!I9=""),"REVIEW",IF(ABS(Raw_Data!G9-Raw_Data!H9-Raw_Data!I9)>1,"EXCEPTION","PASS")) | G9: =IF(OR(Raw_Data!K9="",Raw_Data!J9=""),"REVIEW",IF(Raw_Data!K9>Raw_Data!J9,"EXCEPTION","PASS")) | H9: =IF(Raw_Data!N9="","REVIEW",IF(Raw_Data!N9<0,"EXCEPTION","PASS")) | I9: =IF(Raw_Data!L9="","REVIEW",IF(Raw_Data!L9<=0,"EXCEPTION","PASS")) | J9: =IFERROR(Raw_Data!K9/Raw_Data!J9,"") | K9: =IFERROR(Raw_Data!Q9/Raw_Data!P9,"") | L9: =IFERROR(Raw_Data!O9/Raw_Data!G9,"") | M9: =IFERROR(Raw_Data!O9/Raw_Data!I9,"") | N9: =IFERROR((Raw_Data!M9-Raw_Data!N9)/Raw_Data!G9,"") | O9: =IF(OR(J9="",K9="",L9="",M9="",N9=""),"REVIEW",IF(OR(ABS(J9-Raw_Data!R9)>0.005,ABS(K9-Raw_Data!S9)>0.005,ABS(L9-Raw_Data!T9)>0.005,ABS(M9-Raw_Data!U9)>0.005,ABS(N9-Raw_Data!V9)>0.005),"CHECK","PASS")) | P9: Open
A10: =Raw_Data!A10 | B10: =Raw_Data!B10 | C10: =Raw_Data!D10 | D10: =IF(OR(Raw_Data!G10="",Raw_Data!I10="",Raw_Data!O10=""),"EXCEPTION","PASS") | E10: =IF(COUNTIFS(Raw_Data!A:A,A10,Raw_Data!D:D,C10)>1,"EXCEPTION","PASS") | F10: =IF(OR(Raw_Data!G10="",Raw_Data!H10="",Raw_Data!I10=""),"REVIEW",IF(ABS(Raw_Data!G10-Raw_Data!H10-Raw_Data!I10)>1,"EXCEPTION","PASS")) | G10: =IF(OR(Raw_Data!K10="",Raw_Data!J10=""),"REVIEW",IF(Raw_Data!K10>Raw_Data!J10,"EXCEPTION","PASS")) | H10: =IF(Raw_Data!N10="","REVIEW",IF(Raw_Data!N10<0,"EXCEPTION","PASS")) | I10: =IF(Raw_Data!L10="","REVIEW",IF(Raw_Data!L10<=0,"EXCEPTION","PASS")) | J10: =IFERROR(Raw_Data!K10/Raw_Data!J10,"") | K10: =IFERROR(Raw_Data!Q10/Raw_Data!P10,"") | L10: =IFERROR(Raw_Data!O10/Raw_Data!G10,"") | M10: =IFERROR(Raw_Data!O10/Raw_Data!I10,"") | N10: =IFERROR((Raw_Data!M10-Raw_Data!N10)/Raw_Data!G10,"") | O10: =IF(OR(J10="",K10="",L10="",M10="",N10=""),"REVIEW",IF(OR(ABS(J10-Raw_Data!R10)>0.005,ABS(K10-Raw_Data!S10)>0.005,ABS(L10-Raw_Data!T10)>0.005,ABS(M10-Raw_Data!U10)>0.005,ABS(N10-Raw_Data!V10)>0.005),"CHECK","PASS")) | P10: Open
A11: =Raw_Data!A11 | B11: =Raw_Data!B11 | C11: =Raw_Data!D11 | D11: =IF(OR(Raw_Data!G11="",Raw_Data!I11="",Raw_Data!O11=""),"EXCEPTION","PASS") | E11: =IF(COUNTIFS(Raw_Data!A:A,A11,Raw_Data!D:D,C11)>1,"EXCEPTION","PASS") | F11: =IF(OR(Raw_Data!G11="",Raw_Data!H11="",Raw_Data!I11=""),"REVIEW",IF(ABS(Raw_Data!G11-Raw_Data!H11-Raw_Data!I11)>1,"EXCEPTION","PASS")) | G11: =IF(OR(Raw_Data!K11="",Raw_Data!J11=""),"REVIEW",IF(Raw_Data!K11>Raw_Data!J11,"EXCEPTION","PASS")) | H11: =IF(Raw_Data!N11="","REVIEW",IF(Raw_Data!N11<0,"EXCEPTION","PASS")) | I11: =IF(Raw_Data!L11="","REVIEW",IF(Raw_Data!L11<=0,"EXCEPTION","PASS")) | J11: =IFERROR(Raw_Data!K11/Raw_Data!J11,"") | K11: =IFERROR(Raw_Data!Q11/Raw_Data!P11,"") | L11: =IFERROR(Raw_Data!O11/Raw_Data!G11,"") | M11: =IFERROR(Raw_Data!O11/Raw_Data!I11,"") | N11: =IFERROR((Raw_Data!M11-Raw_Data!N11)/Raw_Data!G11,"") | O11: =IF(OR(J11="",K11="",L11="",M11="",N11=""),"REVIEW",IF(OR(ABS(J11-Raw_Data!R11)>0.005,ABS(K11-Raw_Data!S11)>0.005,ABS(L11-Raw_Data!T11)>0.005,ABS(M11-Raw_Data!U11)>0.005,ABS(N11-Raw_Data!V11)>0.005),"CHECK","PASS")) | P11: Open
A12: =Raw_Data!A12 | B12: =Raw_Data!B12 | C12: =Raw_Data!D12 | D12: =IF(OR(Raw_Data!G12="",Raw_Data!I12="",Raw_Data!O12=""),"EXCEPTION","PASS") | E12: =IF(COUNTIFS(Raw_Data!A:A,A12,Raw_Data!D:D,C12)>1,"EXCEPTION","PASS") | F12: =IF(OR(Raw_Data!G12="",Raw_Data!H12="",Raw_Data!I12=""),"REVIEW",IF(ABS(Raw_Data!G12-Raw_Data!H12-Raw_Data!I12)>1,"EXCEPTION","PASS")) | G12: =IF(OR(Raw_Data!K12="",Raw_Data!J12=""),"REVIEW",IF(Raw_Data!K12>Raw_Data!J12,"EXCEPTION","PASS")) | H12: =IF(Raw_Data!N12="","REVIEW",IF(Raw_Data!N12<0,"EXCEPTION","PASS")) | I12: =IF(Raw_Data!L12="","REVIEW",IF(Raw_Data!L12<=0,"EXCEPTION","PASS")) | J12: =IFERROR(Raw_Data!K12/Raw_Data!J12,"") | K12: =IFERROR(Raw_Data!Q12/Raw_Data!P12,"") | L12: =IFERROR(Raw_Data!O12/Raw_Data!G12,"") | M12: =IFERROR(Raw_Data!O12/Raw_Data!I12,"") | N12: =IFERROR((Raw_Data!M12-Raw_Data!N12)/Raw_Data!G12,"") | O12: =IF(OR(J12="",K12="",L12="",M12="",N12=""),"REVIEW",IF(OR(ABS(J12-Raw_Data!R12)>0.005,ABS(K12-Raw_Data!S12)>0.005,ABS(L12-Raw_Data!T12)>0.005,ABS(M12-Raw_Data!U12)>0.005,ABS(N12-Raw_Data!V12)>0.005),"CHECK","PASS")) | P12: Open
A13: =Raw_Data!A13 | B13: =Raw_Data!B13 | C13: =Raw_Data!D13 | D13: =IF(OR(Raw_Data!G13="",Raw_Data!I13="",Raw_Data!O13=""),"EXCEPTION","PASS") | E13: =IF(COUNTIFS(Raw_Data!A:A,A13,Raw_Data!D:D,C13)>1,"EXCEPTION","PASS") | F13: =IF(OR(Raw_Data!G13="",Raw_Data!H13="",Raw_Data!I13=""),"REVIEW",IF(ABS(Raw_Data!G13-Raw_Data!H13-Raw_Data!I13)>1,"EXCEPTION","PASS")) | G13: =IF(OR(Raw_Data!K13="",Raw_Data!J13=""),"REVIEW",IF(Raw_Data!K13>Raw_Data!J13,"EXCEPTION","PASS")) | H13: =IF(Raw_Data!N13="","REVIEW",IF(Raw_Data!N13<0,"EXCEPTION","PASS")) | I13: =IF(Raw_Data!L13="","REVIEW",IF(Raw_Data!L13<=0,"EXCEPTION","PASS")) | J13: =IFERROR(Raw_Data!K13/Raw_Data!J13,"") | K13: =IFERROR(Raw_Data!Q13/Raw_Data!P13,"") | L13: =IFERROR(Raw_Data!O13/Raw_Data!G13,"") | M13: =IFERROR(Raw_Data!O13/Raw_Data!I13,"") | N13: =IFERROR((Raw_Data!M13-Raw_Data!N13)/Raw_Data!G13,"") | O13: =IF(OR(J13="",K13="",L13="",M13="",N13=""),"REVIEW",IF(OR(ABS(J13-Raw_Data!R13)>0.005,ABS(K13-Raw_Data!S13)>0.005,ABS(L13-Raw_Data!T13)>0.005,ABS(M13-Raw_Data!U13)>0.005,ABS(N13-Raw_Data!V13)>0.005),"CHECK","PASS")) | P13: Open
A14: =Raw_Data!A14 | B14: =Raw_Data!B14 | C14: =Raw_Data!D14 | D14: =IF(OR(Raw_Data!G14="",Raw_Data!I14="",Raw_Data!O14=""),"EXCEPTION","PASS") | E14: =IF(COUNTIFS(Raw_Data!A:A,A14,Raw_Data!D:D,C14)>1,"EXCEPTION","PASS") | F14: =IF(OR(Raw_Data!G14="",Raw_Data!H14="",Raw_Data!I14=""),"REVIEW",IF(ABS(Raw_Data!G14-Raw_Data!H14-Raw_Data!I14)>1,"EXCEPTION","PASS")) | G14: =IF(OR(Raw_Data!K14="",Raw_Data!J14=""),"REVIEW",IF(Raw_Data!K14>Raw_Data!J14,"EXCEPTION","PASS")) | H14: =IF(Raw_Data!N14="","REVIEW",IF(Raw_Data!N14<0,"EXCEPTION","PASS")) | I14: =IF(Raw_Data!L14="","REVIEW",IF(Raw_Data!L14<=0,"EXCEPTION","PASS")) | J14: =IFERROR(Raw_Data!K14/Raw_Data!J14,"") | K14: =IFERROR(Raw_Data!Q14/Raw_Data!P14,"") | L14: =IFERROR(Raw_Data!O14/Raw_Data!G14,"") | M14: =IFERROR(Raw_Data!O14/Raw_Data!I14,"") | N14: =IFERROR((Raw_Data!M14-Raw_Data!N14)/Raw_Data!G14,"") | O14: =IF(OR(J14="",K14="",L14="",M14="",N14=""),"REVIEW",IF(OR(ABS(J14-Raw_Data!R14)>0.005,ABS(K14-Raw_Data!S14)>0.005,ABS(L14-Raw_Data!T14)>0.005,ABS(M14-Raw_Data!U14)>0.005,ABS(N14-Raw_Data!V14)>0.005),"CHECK","PASS")) | P14: Open

Sheet Exception_Log
A1: exception_id | B1: bank_id | C1: report_date | D1: issue_type | E1: severity | F1: detected_by | G1: investigation_notes | H1: proposed_action | I1: status | J1: reviewer | K1: resolution_date
A2: EX001 | B2: B003 | C2: 2025-03-31 | D2: MISSING_TOTAL_EQUITY | E2: High | F2: Excel/SQL | G2: Total equity is blank in raw feed. | H2: Check source report; populate only after source verification. | I2: Open
A3: EX002 | B3: B007 | C3: 2025-03-31 | D3: MISSING_NET_INCOME | E3: High | F3: Excel/SQL | G3: Net income is blank in raw feed. | H3: Verify against source financial statement. | I3: Open
A4: EX003 | B4: B002 | C4: 2025-03-31 | D4: DUPLICATE_BANK_PERIOD | E4: High | F4: Excel/SQL | G4: Two rows exist for same bank and period from different source labels. | H4: Compare source lineage; retain traceable record(s), do not blindly delete. | I4: Open
A5: EX004 | B5: B004 | C5: 2025-03-31 | D5: BALANCE_SHEET_MISMATCH | E5: High | F5: Excel/SQL | G5: Assets differ from liabilities plus equity. | H5: Re-check source statement and mapping. | I5: Open
A6: EX005 | B6: B005 | C6: 2025-03-31 | D6: NPL_EXCEEDS_GROSS_LOANS | E6: High | F6: Excel/SQL | G6: NPL amount exceeds gross loans. | H6: Check units, field mapping, and source values. | I6: Open
A7: EX006 | B7: B006 | C7: 2025-03-31 | D7: NEGATIVE_INTEREST_EXPENSE | E7: Medium | F7: Excel/SQL | G7: Interest expense is negative; may be sign convention or data issue. | H7: Confirm source sign convention before changing. | I7: Open
A8: EX007 | B8: B009 | C8: 2025-03-31 | D8: NONPOSITIVE_DEPOSITS | E8: High | F8: Excel/SQL | G8: Deposits are zero; validate plausibility and ratio denominators. | H8: Verify source disclosure; ratios with zero denominator must be null/flagged. | I8: Open
A9: EX008 | B9: B008 | C9: 2025-03-31 | D9: SOURCE_ASSET_DISCREPANCY | E9: High | F9: Source reconciliation | G9: Annual report and vendor feed assets differ. | H9: Use source hierarchy and document the chosen value. | I9: Open
A10: EX009 | B10: B011 | C10: 2025-03-31 | D10: SOURCE_NET_INCOME_DISCREPANCY | E10: Medium | F10: Source reconciliation | G10: Annual report and vendor feed net income differ. | H10: Reconcile against report notes and reporting period. | I10: Open

Sheet Read_Me
A1: BANK FINANCIAL DATA QUALITY & VALIDATION PROJECT
A2: Purpose | B2: Practice bank financial data quality checks using fictional data only.
A3: Workbook workflow | B3: Raw_Data -> Validation -> Exception_Log -> Dashboard. Source_Comparison contains two-source reconciliation rows.
A4: Important | B4: Raw_Data contains intentional defects. Do not overwrite source values to make checks pass.
A5: Excel formulas | B5: Missing: IF(OR(cell="",...),"EXCEPTION","PASS"); duplicates: COUNTIFS by bank_id + report_date; balance sheet: ABS(assets-liabilities-equity)>1.
A6: Ratios | B6: NPL ratio = NPL amount / gross loans; CAR = regulatory capital / risk-weighted assets; ROA = net income / total assets; ROE = net income / total equity; NIM proxy = (interest income - interest expense) / total assets.
A7: NIM caveat | B7: Industry NIM normally uses net interest income divided by average interest-earning assets. This dataset lacks average earning assets, so the workbook labels this as a proxy.
A8: Review discipline | B8: Investigate against an authoritative source; document source, date, reviewer, and action. A failed rule is an exception, not automatic proof that a value is wrong.
A9: PostgreSQL | B9: Create tables with bank_data_quality.sql, then import the CSVs. SQL comments contain sample psql \\copy commands.
A10: Expected seeded issues | B10: Missing equity (B003); missing net income (B007); duplicate bank-period (B002); balance sheet mismatch (B004); NPL exceeds loans (B005); negative interest expense (B006); zero deposits (B009); source discrepancies (B008 assets, B011 net income).
A11: Ratio interpretation | B11: NPL and CAR use bank-specific definitions and regulatory rules in real work. This project uses simplified definitions for learning, not credit decisions.
A12: Portfolio ethics | B12: Clearly label all data as synthetic. Do not claim these results came from Moody's or from real banks.
